py_yettagam/__init__.py
py_yettagam/api/__init__.py
py_yettagam/api/listener/__init__.py
py_yettagam/api/listener/v1.py
py_yettagam/substrate/__init__.py
py_yettagam/substrate/committer.py
py_yettagam/substrate/decorators.py
py_yettagam/substrate/downloader.py
py_yettagam/substrate/exceptions.py
py_yettagam/substrate/listener.py
py_yettagam-0.0.2.28.dist-info/LICENSE
py_yettagam-0.0.2.28.dist-info/METADATA
py_yettagam-0.0.2.28.dist-info/WHEEL
py_yettagam-0.0.2.28.dist-info/top_level.txt
py_yettagam-0.0.2.28.dist-info/RECORD
