Metadata-Version: 2.1
Name: py-yettagam
Version: 0.0.2.28
Summary: Python package for Metarium's Storage Layer
Author: MetariumProject
Project-URL: Homepage, https://github.com/MetariumProject/py-yettagam
Project-URL: Bug Tracker, https://github.com/MetariumProject/py-yettagam/issues
Classifier: Programming Language :: Python :: 3
Classifier: License :: OSI Approved :: MIT License
Classifier: Operating System :: OS Independent
Requires-Python: >=3.9
License-File: LICENSE
Requires-Dist: substrate-interface (==1.4.0)
Requires-Dist: blake3 (==0.3.3)
Requires-Dist: tinydb (==4.7.1)
Requires-Dist: paramiko (==3.1.0)
Requires-Dist: sshpubkeys (==3.3.1)
Requires-Dist: fastapi (==0.95.0)
Requires-Dist: uvicorn (==0.21.1)
